{
    "black_list": [
      {
        "s": "AMEX:AST",
        "f": [
          "no longer trading"
        ]
      },
      {
        "s": "AMEX:BRGL",
        "f": [
          "no longer trading"
        ]
      },
      {
        "s": "AMEX:MFDX",
        "f": [
          "empty symbol"
        ]
      },
      {
        "s": "AMEX:MSUS",
        "f": [
          "no longer trading"
        ]
      },
      {
        "s": "AMEX:OVOL",
        "f": [
          "no longer trading"
        ]
      },
      {
        "s": "AMEX:PQLC",
        "f": [
          "no longer trading"
        ]
      },
      {
        "s": "AMEX:PQSV",
        "f": [
          "no longer trading"
        ]
      },
      {
        "s": "AMEX:RBUS",
        "f": [
          "no longer trading"
        ]
      },
      {
        "s": "AMEX:YCOM",
        "f": [
          "no longer trading"
        ]
      },
      {
        "s": "CME:E41!",
        "f": [
          "no longer trading"
        ]
      },
      {
        "s": "CME:E4M2019",
        "f": [
          "no longer trading"
        ]
      },
      {
        "s": "CME:E4U2019",
        "f": [
          "no longer trading"
        ]
      },
      {
        "s": "CME:E4Z2019",
        "f": [
          "no longer trading"
        ]
      },
      {
        "s": "CME:E51!",
        "f": [
          "no longer trading"
        ]
      },
      {
        "s": "CME:E5M2019",
        "f": [
          "no longer trading"
        ]
      },
      {
        "s": "CME:E5U2019",
        "f": [
          "no longer trading"
        ]
      },
      {
        "s": "CME:E5Z2019",
        "f": [
          "no longer trading"
        ]
      },
      {
        "s": "CME:I91!",
        "f": [
          "equal bars"
        ]
      },
      {
        "s": "CME:I9K2019",
        "f": [
          "equal bars"
        ]
      },
      {
        "s": "CME:T6K2020",
        "f": [
          "empty symbol"
        ]
      },
      {
        "s": "COMEX:LD1!",
        "f": [
          "equal bars"
        ]
      },
      {
        "s": "COMEX:LDJ2019",
        "f": [
          "equal bars"
        ]
      },
      {
        "s": "COMEX:LDK2019",
        "f": [
          "equal bars"
        ]
      },
      {
        "s": "COMEX:LDM2019",
        "f": [
          "equal bars"
        ]
      },
      {
        "s": "COMEX:LDN2019",
        "f": [
          "equal bars"
        ]
      },
      {
        "s": "COMEX:LDQ2019",
        "f": [
          "equal bars"
        ]
      },
      {
        "s": "COMEX:LDU2019",
        "f": [
          "equal bars"
        ]
      },
      {
        "s": "COMEX:LDV2019",
        "f": [
          "equal bars"
        ]
      },
      {
        "s": "COMEX:LDX2019",
        "f": [
          "equal bars"
        ]
      },
      {
        "s": "COMEX:LDZ2019",
        "f": [
          "equal bars"
        ]
      },
      {
        "s": "COMEX_MINI:QCJ2019",
        "f": [
          "no longer trading"
        ]
      },
      {
        "s": "COMEX_MINI:QOJ2019",
        "f": [
          "no longer trading"
        ]
      },
      {
        "s": "NASDAQ:ABP",
        "f": [
          "empty symbol"
        ]
      },
      {
        "s": "NASDAQ:ACAM",
        "f": [
          "empty symbol"
        ]
      },
      {
        "s": "NASDAQ:ALIT",
        "f": [
          "empty symbol"
        ]
      },
      {
        "s": "NASDAQ:AMAL",
        "f": [
          "empty symbol"
        ]
      },
      {
        "s": "NASDAQ:BCACU",
        "f": [
          "no longer trading"
        ]
      },
      {
        "s": "NASDAQ:BFL",
        "f": [
          "empty symbol"
        ]
      },
      {
        "s": "NASDAQ:BRACU",
        "f": [
          "no longer trading"
        ]
      },
      {
        "s": "NASDAQ:BVNSC",
        "f": [
          "empty symbol"
        ]
      },
      {
        "s": "NASDAQ:CBUS",
        "f": [
          "empty symbol"
        ]
      },
      {
        "s": "NASDAQ:CGVIC",
        "f": [
          "empty symbol"
        ]
      },
      {
        "s": "NASDAQ:CIVEC",
        "f": [
          "empty symbol"
        ]
      },
      {
        "s": "NASDAQ:CMCTP",
        "f": [
          "no longer trading"
        ]
      },
      {
        "s": "NASDAQ:CNACU",
        "f": [
          "no longer trading"
        ]
      },
      {
        "s": "NASDAQ:CRSA",
        "f": [
          "empty symbol"
        ]
      },
      {
        "s": "NASDAQ:CRUSC",
        "f": [
          "empty symbol"
        ]
      },
      {
        "s": "NASDAQ:DDOC",
        "f": [
          "empty symbol"
        ]
      },
      {
        "s": "NASDAQ:DFBHU",
        "f": [
          "no longer trading"
        ]
      },
      {
        "s": "NASDAQ:EHR",
        "f": [
          "empty symbol"
        ]
      },
      {
        "s": "NASDAQ:EVFTC",
        "f": [
          "empty symbol"
        ]
      },
      {
        "s": "NASDAQ:EVGBC",
        "f": [
          "empty symbol"
        ]
      },
      {
        "s": "NASDAQ:EVLMC",
        "f": [
          "empty symbol"
        ]
      },
      {
        "s": "NASDAQ:EVSTC",
        "f": [
          "empty symbol"
        ]
      },
      {
        "s": "NASDAQ:FTEO",
        "f": [
          "no longer trading"
        ]
      },
      {
        "s": "NASDAQ:GNLN",
        "f": [
          "empty symbol"
        ]
      },
      {
        "s": "NASDAQ:HFGIC",
        "f": [
          "empty symbol"
        ]
      },
      {
        "s": "NASDAQ:HOOK",
        "f": [
          "empty symbol"
        ]
      },
      {
        "s": "NASDAQ:HUNT",
        "f": [
          "no longer trading"
        ]
      },
      {
        "s": "NASDAQ:HUNTU",
        "f": [
          "no longer trading"
        ]
      },
      {
        "s": "NASDAQ:IBEX",
        "f": [
          "empty symbol"
        ]
      },
      {
        "s": "NASDAQ:INTLL",
        "f": [
          "empty symbol"
        ]
      },
      {
        "s": "NASDAQ:IVENC",
        "f": [
          "empty symbol"
        ]
      },
      {
        "s": "NASDAQ:IVFGC",
        "f": [
          "empty symbol"
        ]
      },
      {
        "s": "NASDAQ:IVFVC",
        "f": [
          "empty symbol"
        ]
      },
      {
        "s": "NASDAQ:JSYNU",
        "f": [
          "no longer trading"
        ]
      },
      {
        "s": "NASDAQ:KELYB",
        "f": [
          "no longer trading"
        ]
      },
      {
        "s": "NASDAQ:KPFS",
        "f": [
          "no longer trading"
        ]
      },
      {
        "s": "NASDAQ:OKDCC",
        "f": [
          "no longer trading"
        ]
      },
      {
        "s": "NASDAQ:PSET",
        "f": [
          "no longer trading"
        ]
      },
      {
        "s": "NASDAQ:SOHOL",
        "f": [
          "empty symbol"
        ]
      },
      {
        "s": "NASDAQ:SVA",
        "f": [
          "no longer trading"
        ]
      },
      {
        "s": "NASDAQ:TOTAU",
        "f": [
          "no longer trading"
        ]
      },
      {
        "s": "NASDAQ:USATP",
        "f": [
          "no longer trading"
        ]
      },
      {
        "s": "NASDAQ:VETS",
        "f": [
          "no longer trading"
        ]
      },
      {
        "s": "NASDAQ:VTUS",
        "f": [
          "empty symbol"
        ]
      },
      {
        "s": "NASDAQ:WRLSU",
        "f": [
          "no longer trading"
        ]
      },
      {
        "s": "NASDAQ:XM",
        "f": [
          "empty symbol"
        ]
      },
      {
        "s": "NASDAQ:YPRO",
        "f": [
          "empty symbol"
        ]
      },
      {
        "s": "NASDAQ:ZM",
        "f": [
          "empty symbol"
        ]
      },
      {
        "s": "NYMEX:JMJ1!",
        "f": [
          "no longer trading"
        ]
      },
      {
        "s": "NYMEX:JMJF2021",
        "f": [
          "no longer trading"
        ]
      },
      {
        "s": "NYMEX:JMJF2022",
        "f": [
          "no longer trading"
        ]
      },
      {
        "s": "NYMEX:JMJF2023",
        "f": [
          "no longer trading"
        ]
      },
      {
        "s": "NYMEX:JMJF2024",
        "f": [
          "empty symbol"
        ]
      },
      {
        "s": "NYMEX:JMJF2025",
        "f": [
          "empty symbol"
        ]
      },
      {
        "s": "NYMEX:JMJG2021",
        "f": [
          "no longer trading"
        ]
      },
      {
        "s": "NYMEX:JMJG2022",
        "f": [
          "no longer trading"
        ]
      },
      {
        "s": "NYMEX:JMJG2023",
        "f": [
          "no longer trading"
        ]
      },
      {
        "s": "NYMEX:JMJG2024",
        "f": [
          "empty symbol"
        ]
      },
      {
        "s": "NYMEX:JMJG2025",
        "f": [
          "empty symbol"
        ]
      },
      {
        "s": "NYMEX:JMJH2021",
        "f": [
          "no longer trading"
        ]
      },
      {
        "s": "NYMEX:JMJH2022",
        "f": [
          "no longer trading"
        ]
      },
      {
        "s": "NYMEX:JMJH2023",
        "f": [
          "no longer trading"
        ]
      },
      {
        "s": "NYMEX:JMJH2024",
        "f": [
          "empty symbol"
        ]
      },
      {
        "s": "NYMEX:JMJH2025",
        "f": [
          "empty symbol"
        ]
      },
      {
        "s": "NYMEX:JMJJ2019",
        "f": [
          "no longer trading"
        ]
      },
      {
        "s": "NYMEX:JMJJ2021",
        "f": [
          "no longer trading"
        ]
      },
      {
        "s": "NYMEX:JMJJ2022",
        "f": [
          "no longer trading"
        ]
      },
      {
        "s": "NYMEX:JMJJ2023",
        "f": [
          "no longer trading"
        ]
      },
      {
        "s": "NYMEX:JMJJ2024",
        "f": [
          "empty symbol"
        ]
      },
      {
        "s": "NYMEX:JMJJ2025",
        "f": [
          "empty symbol"
        ]
      },
      {
        "s": "NYMEX:JMJK2019",
        "f": [
          "no longer trading"
        ]
      },
      {
        "s": "NYMEX:JMJK2021",
        "f": [
          "no longer trading"
        ]
      },
      {
        "s": "NYMEX:JMJK2022",
        "f": [
          "no longer trading"
        ]
      },
      {
        "s": "NYMEX:JMJK2023",
        "f": [
          "no longer trading"
        ]
      },
      {
        "s": "NYMEX:JMJK2024",
        "f": [
          "empty symbol"
        ]
      },
      {
        "s": "NYMEX:JMJK2025",
        "f": [
          "empty symbol"
        ]
      },
      {
        "s": "NYMEX:JMJM2019",
        "f": [
          "no longer trading"
        ]
      },
      {
        "s": "NYMEX:JMJM2021",
        "f": [
          "no longer trading"
        ]
      },
      {
        "s": "NYMEX:JMJM2022",
        "f": [
          "no longer trading"
        ]
      },
      {
        "s": "NYMEX:JMJM2023",
        "f": [
          "no longer trading"
        ]
      },
      {
        "s": "NYMEX:JMJM2024",
        "f": [
          "empty symbol"
        ]
      },
      {
        "s": "NYMEX:JMJM2025",
        "f": [
          "empty symbol"
        ]
      },
      {
        "s": "NYMEX:JMJN2019",
        "f": [
          "no longer trading"
        ]
      },
      {
        "s": "NYMEX:JMJN2021",
        "f": [
          "no longer trading"
        ]
      },
      {
        "s": "NYMEX:JMJN2022",
        "f": [
          "no longer trading"
        ]
      },
      {
        "s": "NYMEX:JMJN2023",
        "f": [
          "no longer trading"
        ]
      },
      {
        "s": "NYMEX:JMJN2024",
        "f": [
          "empty symbol"
        ]
      },
      {
        "s": "NYMEX:JMJN2025",
        "f": [
          "no longer trading"
        ]
      },
      {
        "s": "NYMEX:JMJQ2019",
        "f": [
          "no longer trading"
        ]
      },
      {
        "s": "NYMEX:JMJQ2021",
        "f": [
          "no longer trading"
        ]
      },
      {
        "s": "NYMEX:JMJQ2022",
        "f": [
          "no longer trading"
        ]
      },
      {
        "s": "NYMEX:JMJQ2023",
        "f": [
          "no longer trading"
        ]
      },
      {
        "s": "NYMEX:JMJQ2024",
        "f": [
          "empty symbol"
        ]
      },
      {
        "s": "NYMEX:JMJQ2025",
        "f": [
          "empty symbol"
        ]
      },
      {
        "s": "NYMEX:JMJU2019",
        "f": [
          "no longer trading"
        ]
      },
      {
        "s": "NYMEX:JMJU2021",
        "f": [
          "no longer trading"
        ]
      },
      {
        "s": "NYMEX:JMJU2022",
        "f": [
          "no longer trading"
        ]
      },
      {
        "s": "NYMEX:JMJU2023",
        "f": [
          "no longer trading"
        ]
      },
      {
        "s": "NYMEX:JMJU2024",
        "f": [
          "empty symbol"
        ]
      },
      {
        "s": "NYMEX:JMJU2025",
        "f": [
          "no longer trading"
        ]
      },
      {
        "s": "NYMEX:JMJV2019",
        "f": [
          "no longer trading"
        ]
      },
      {
        "s": "NYMEX:JMJV2021",
        "f": [
          "no longer trading"
        ]
      },
      {
        "s": "NYMEX:JMJV2022",
        "f": [
          "no longer trading"
        ]
      },
      {
        "s": "NYMEX:JMJV2023",
        "f": [
          "no longer trading"
        ]
      },
      {
        "s": "NYMEX:JMJV2024",
        "f": [
          "empty symbol"
        ]
      },
      {
        "s": "NYMEX:JMJV2025",
        "f": [
          "no longer trading"
        ]
      },
      {
        "s": "NYMEX:JMJX2019",
        "f": [
          "no longer trading"
        ]
      },
      {
        "s": "NYMEX:JMJX2021",
        "f": [
          "no longer trading"
        ]
      },
      {
        "s": "NYMEX:JMJX2022",
        "f": [
          "no longer trading"
        ]
      },
      {
        "s": "NYMEX:JMJX2023",
        "f": [
          "no longer trading"
        ]
      },
      {
        "s": "NYMEX:JMJX2024",
        "f": [
          "empty symbol"
        ]
      },
      {
        "s": "NYMEX:JMJX2025",
        "f": [
          "empty symbol"
        ]
      },
      {
        "s": "NYMEX:JMJZ2019",
        "f": [
          "no longer trading"
        ]
      },
      {
        "s": "NYMEX:JMJZ2021",
        "f": [
          "no longer trading"
        ]
      },
      {
        "s": "NYMEX:JMJZ2022",
        "f": [
          "no longer trading"
        ]
      },
      {
        "s": "NYMEX:JMJZ2023",
        "f": [
          "no longer trading"
        ]
      },
      {
        "s": "NYMEX:JMJZ2024",
        "f": [
          "empty symbol"
        ]
      },
      {
        "s": "NYMEX:JMJZ2025",
        "f": [
          "no longer trading"
        ]
      },
      {
        "s": "NYMEX:TIC1!",
        "f": [
          "no longer trading"
        ]
      },
      {
        "s": "NYMEX:TICF2020",
        "f": [
          "empty symbol"
        ]
      },
      {
        "s": "NYMEX:TICF2021",
        "f": [
          "empty symbol"
        ]
      },
      {
        "s": "NYMEX:TICG2020",
        "f": [
          "empty symbol"
        ]
      },
      {
        "s": "NYMEX:TICG2021",
        "f": [
          "empty symbol"
        ]
      },
      {
        "s": "NYMEX:TICH2020",
        "f": [
          "empty symbol"
        ]
      },
      {
        "s": "NYMEX:TICH2021",
        "f": [
          "empty symbol"
        ]
      },
      {
        "s": "NYMEX:TICJ2019",
        "f": [
          "empty symbol"
        ]
      },
      {
        "s": "NYMEX:TICJ2020",
        "f": [
          "empty symbol"
        ]
      },
      {
        "s": "NYMEX:TICJ2021",
        "f": [
          "empty symbol"
        ]
      },
      {
        "s": "NYMEX:TICK2019",
        "f": [
          "empty symbol"
        ]
      },
      {
        "s": "NYMEX:TICK2020",
        "f": [
          "empty symbol"
        ]
      },
      {
        "s": "NYMEX:TICK2021",
        "f": [
          "empty symbol"
        ]
      },
      {
        "s": "NYMEX:TICM2019",
        "f": [
          "empty symbol"
        ]
      },
      {
        "s": "NYMEX:TICM2020",
        "f": [
          "empty symbol"
        ]
      },
      {
        "s": "NYMEX:TICM2021",
        "f": [
          "empty symbol"
        ]
      },
      {
        "s": "NYMEX:TICN2019",
        "f": [
          "empty symbol"
        ]
      },
      {
        "s": "NYMEX:TICN2020",
        "f": [
          "empty symbol"
        ]
      },
      {
        "s": "NYMEX:TICN2021",
        "f": [
          "empty symbol"
        ]
      },
      {
        "s": "NYMEX:TICQ2019",
        "f": [
          "empty symbol"
        ]
      },
      {
        "s": "NYMEX:TICQ2020",
        "f": [
          "empty symbol"
        ]
      },
      {
        "s": "NYMEX:TICQ2021",
        "f": [
          "empty symbol"
        ]
      },
      {
        "s": "NYMEX:TICU2019",
        "f": [
          "empty symbol"
        ]
      },
      {
        "s": "NYMEX:TICU2020",
        "f": [
          "empty symbol"
        ]
      },
      {
        "s": "NYMEX:TICU2021",
        "f": [
          "empty symbol"
        ]
      },
      {
        "s": "NYMEX:TICV2019",
        "f": [
          "empty symbol"
        ]
      },
      {
        "s": "NYMEX:TICV2020",
        "f": [
          "empty symbol"
        ]
      },
      {
        "s": "NYMEX:TICV2021",
        "f": [
          "empty symbol"
        ]
      },
      {
        "s": "NYMEX:TICX2019",
        "f": [
          "empty symbol"
        ]
      },
      {
        "s": "NYMEX:TICX2020",
        "f": [
          "empty symbol"
        ]
      },
      {
        "s": "NYMEX:TICX2021",
        "f": [
          "empty symbol"
        ]
      },
      {
        "s": "NYMEX:TICZ2019",
        "f": [
          "empty symbol"
        ]
      },
      {
        "s": "NYMEX:TICZ2020",
        "f": [
          "empty symbol"
        ]
      },
      {
        "s": "NYMEX:TICZ2021",
        "f": [
          "empty symbol"
        ]
      },
      {
        "s": "NYSE:ABEV",
        "f": [
          "empty symbol"
        ]
      },
      {
        "s": "NYSE:ACP",
        "f": [
          "empty symbol"
        ]
      },
      {
        "s": "NYSE:ADNT",
        "f": [
          "empty symbol"
        ]
      },
      {
        "s": "NYSE:ADS",
        "f": [
          "empty symbol"
        ]
      },
      {
        "s": "NYSE:ADT",
        "f": [
          "empty symbol"
        ]
      },
      {
        "s": "NYSE:AEE",
        "f": [
          "empty symbol"
        ]
      },
      {
        "s": "NYSE:AEP",
        "f": [
          "empty symbol"
        ]
      },
      {
        "s": "NYSE:AFB",
        "f": [
          "empty symbol"
        ]
      },
      {
        "s": "NYSE:AFI",
        "f": [
          "empty symbol"
        ]
      },
      {
        "s": "NYSE:AFL",
        "f": [
          "empty symbol"
        ]
      },
      {
        "s": "NYSE:AFT",
        "f": [
          "empty symbol"
        ]
      },
      {
        "s": "NYSE:AGCO",
        "f": [
          "empty symbol"
        ]
      },
      {
        "s": "NYSE:AGD",
        "f": [
          "empty symbol"
        ]
      },
      {
        "s": "NYSE:AGI",
        "f": [
          "empty symbol"
        ]
      },
      {
        "s": "NYSE:AGM",
        "f": [
          "empty symbol"
        ]
      },
      {
        "s": "NYSE:AGM/PA",
        "f": [
          "empty symbol"
        ]
      },
      {
        "s": "NYSE:AGM/PB",
        "f": [
          "empty symbol"
        ]
      },
      {
        "s": "NYSE:AGM/PC",
        "f": [
          "empty symbol"
        ]
      },
      {
        "s": "NYSE:AGN",
        "f": [
          "empty symbol"
        ]
      },
      {
        "s": "NYSE:AGO/PB",
        "f": [
          "empty symbol"
        ]
      },
      {
        "s": "NYSE:AGO/PE",
        "f": [
          "empty symbol"
        ]
      },
      {
        "s": "NYSE:AGO/PF",
        "f": [
          "empty symbol"
        ]
      },
      {
        "s": "NYSE:AGS",
        "f": [
          "empty symbol"
        ]
      },
      {
        "s": "NYSE:AHC",
        "f": [
          "empty symbol"
        ]
      },
      {
        "s": "NYSE:AHH",
        "f": [
          "empty symbol"
        ]
      },
      {
        "s": "NYSE:AHL",
        "f": [
          "empty symbol"
        ]
      },
      {
        "s": "NYSE:AHL/PC",
        "f": [
          "empty symbol"
        ]
      },
      {
        "s": "NYSE:AHL/PD",
        "f": [
          "empty symbol"
        ]
      },
      {
        "s": "NYSE:AIC",
        "f": [
          "empty symbol"
        ]
      },
      {
        "s": "NYSE:AIF",
        "f": [
          "empty symbol"
        ]
      },
      {
        "s": "NYSE:AIG",
        "f": [
          "empty symbol"
        ]
      },
      {
        "s": "NYSE:AIG/PA",
        "f": [
          "empty symbol"
        ]
      },
      {
        "s": "NYSE:AIN",
        "f": [
          "empty symbol"
        ]
      },
      {
        "s": "NYSE:AIT",
        "f": [
          "empty symbol"
        ]
      },
      {
        "s": "NYSE:AIV",
        "f": [
          "empty symbol"
        ]
      },
      {
        "s": "NYSE:AIW",
        "f": [
          "empty symbol"
        ]
      },
      {
        "s": "NYSE:AJX",
        "f": [
          "empty symbol"
        ]
      },
      {
        "s": "NYSE:AKO.A",
        "f": [
          "empty symbol"
        ]
      },
      {
        "s": "NYSE:AKO.B",
        "f": [
          "empty symbol"
        ]
      },
      {
        "s": "NYSE:AKP",
        "f": [
          "empty symbol"
        ]
      },
      {
        "s": "NYSE:AKR",
        "f": [
          "empty symbol"
        ]
      },
      {
        "s": "NYSE:AKS",
        "f": [
          "empty symbol"
        ]
      },
      {
        "s": "NYSE:ALB",
        "f": [
          "empty symbol"
        ]
      },
      {
        "s": "NYSE:ALG",
        "f": [
          "empty symbol"
        ]
      },
      {
        "s": "NYSE:ALK",
        "f": [
          "empty symbol"
        ]
      },
      {
        "s": "NYSE:ALL",
        "f": [
          "empty symbol"
        ]
      },
      {
        "s": "NYSE:ALL/PD",
        "f": [
          "empty symbol"
        ]
      },
      {
        "s": "NYSE:ALL/PE",
        "f": [
          "empty symbol"
        ]
      },
      {
        "s": "NYSE:ALLY",
        "f": [
          "empty symbol"
        ]
      },
      {
        "s": "NYSE:ALV",
        "f": [
          "empty symbol"
        ]
      },
      {
        "s": "NYSE:ALX",
        "f": [
          "empty symbol"
        ]
      },
      {
        "s": "NYSE:AMBR",
        "f": [
          "empty symbol"
        ]
      },
      {
        "s": "NYSE:AME",
        "f": [
          "empty symbol"
        ]
      },
      {
        "s": "NYSE:AMG",
        "f": [
          "empty symbol"
        ]
      },
      {
        "s": "NYSE:AMH",
        "f": [
          "empty symbol"
        ]
      },
      {
        "s": "NYSE:AMH/PD",
        "f": [
          "empty symbol"
        ]
      },
      {
        "s": "NYSE:AMH/PE",
        "f": [
          "empty symbol"
        ]
      },
      {
        "s": "NYSE:AMH/PH",
        "f": [
          "empty symbol"
        ]
      },
      {
        "s": "NYSE:AMID",
        "f": [
          "empty symbol"
        ]
      },
      {
        "s": "NYSE:AMN",
        "f": [
          "empty symbol"
        ]
      },
      {
        "s": "NYSE:AMOV",
        "f": [
          "empty symbol"
        ]
      },
      {
        "s": "NYSE:AMP",
        "f": [
          "empty symbol"
        ]
      },
      {
        "s": "NYSE:AMRX",
        "f": [
          "empty symbol"
        ]
      },
      {
        "s": "NYSE:AMX",
        "f": [
          "empty symbol"
        ]
      },
      {
        "s": "NYSE:ANF",
        "f": [
          "empty symbol"
        ]
      },
      {
        "s": "NYSE:ANH",
        "f": [
          "empty symbol"
        ]
      },
      {
        "s": "NYSE:AON",
        "f": [
          "empty symbol"
        ]
      },
      {
        "s": "NYSE:APA",
        "f": [
          "empty symbol"
        ]
      },
      {
        "s": "NYSE:APH",
        "f": [
          "empty symbol"
        ]
      },
      {
        "s": "NYSE:APO",
        "f": [
          "empty symbol"
        ]
      },
      {
        "s": "NYSE:APY",
        "f": [
          "empty symbol"
        ]
      },
      {
        "s": "NYSE:AQN",
        "f": [
          "empty symbol"
        ]
      },
      {
        "s": "NYSE:AQNA",
        "f": [
          "empty symbol"
        ]
      },
      {
        "s": "NYSE:AQUA",
        "f": [
          "empty symbol"
        ]
      },
      {
        "s": "NYSE:ARA",
        "f": [
          "empty symbol"
        ]
      },
      {
        "s": "NYSE:ARC",
        "f": [
          "empty symbol"
        ]
      },
      {
        "s": "NYSE:ARD",
        "f": [
          "empty symbol"
        ]
      },
      {
        "s": "NYSE:ARE",
        "f": [
          "empty symbol"
        ]
      },
      {
        "s": "NYSE:ARE/PD",
        "f": [
          "empty symbol"
        ]
      },
      {
        "s": "NYSE:ARI",
        "f": [
          "empty symbol"
        ]
      },
      {
        "s": "NYSE:ARR",
        "f": [
          "empty symbol"
        ]
      },
      {
        "s": "NYSE:ARW",
        "f": [
          "empty symbol"
        ]
      },
      {
        "s": "NYSE:ASB",
        "f": [
          "empty symbol"
        ]
      },
      {
        "s": "NYSE:ASG",
        "f": [
          "empty symbol"
        ]
      },
      {
        "s": "NYSE:ASGN",
        "f": [
          "empty symbol"
        ]
      },
      {
        "s": "NYSE:ASH",
        "f": [
          "empty symbol"
        ]
      },
      {
        "s": "NYSE:ASIX",
        "f": [
          "empty symbol"
        ]
      },
      {
        "s": "NYSE:ASPN",
        "f": [
          "empty symbol"
        ]
      },
      {
        "s": "NYSE:ASR",
        "f": [
          "empty symbol"
        ]
      },
      {
        "s": "NYSE:ASX",
        "f": [
          "empty symbol"
        ]
      },
      {
        "s": "NYSE:ATH",
        "f": [
          "empty symbol"
        ]
      },
      {
        "s": "NYSE:ATI",
        "f": [
          "empty symbol"
        ]
      },
      {
        "s": "NYSE:ATO",
        "f": [
          "empty symbol"
        ]
      },
      {
        "s": "NYSE:ATR",
        "f": [
          "empty symbol"
        ]
      },
      {
        "s": "NYSE:ATV",
        "f": [
          "empty symbol"
        ]
      },
      {
        "s": "NYSE:AVA",
        "f": [
          "empty symbol"
        ]
      },
      {
        "s": "NYSE:AVB",
        "f": [
          "empty symbol"
        ]
      },
      {
        "s": "NYSE:AVD",
        "f": [
          "empty symbol"
        ]
      },
      {
        "s": "NYSE:AVH",
        "f": [
          "empty symbol"
        ]
      },
      {
        "s": "NYSE:AVK",
        "f": [
          "empty symbol"
        ]
      },
      {
        "s": "NYSE:AVP",
        "f": [
          "empty symbol"
        ]
      },
      {
        "s": "NYSE:AVX",
        "f": [
          "empty symbol"
        ]
      },
      {
        "s": "NYSE:AVY",
        "f": [
          "empty symbol"
        ]
      },
      {
        "s": "NYSE:AWF",
        "f": [
          "empty symbol"
        ]
      },
      {
        "s": "NYSE:AWI",
        "f": [
          "empty symbol"
        ]
      },
      {
        "s": "NYSE:AWP",
        "f": [
          "empty symbol"
        ]
      },
      {
        "s": "NYSE:AWR",
        "f": [
          "empty symbol"
        ]
      },
      {
        "s": "NYSE:AXE",
        "f": [
          "empty symbol"
        ]
      },
      {
        "s": "NYSE:AXL",
        "f": [
          "empty symbol"
        ]
      },
      {
        "s": "NYSE:AXO",
        "f": [
          "empty symbol"
        ]
      },
      {
        "s": "NYSE:AXP",
        "f": [
          "empty symbol"
        ]
      },
      {
        "s": "NYSE:AXR",
        "f": [
          "empty symbol"
        ]
      },
      {
        "s": "NYSE:AXS",
        "f": [
          "empty symbol"
        ]
      },
      {
        "s": "NYSE:AXS/PE",
        "f": [
          "empty symbol"
        ]
      },
      {
        "s": "NYSE:AYR",
        "f": [
          "empty symbol"
        ]
      },
      {
        "s": "NYSE:AZN",
        "f": [
          "empty symbol"
        ]
      },
      {
        "s": "NYSE:AZZ",
        "f": [
          "empty symbol"
        ]
      },
      {
        "s": "NYSE:BAC",
        "f": [
          "empty symbol"
        ]
      },
      {
        "s": "NYSE:BAC/PA",
        "f": [
          "empty symbol"
        ]
      },
      {
        "s": "NYSE:BAC/PB",
        "f": [
          "empty symbol"
        ]
      },
      {
        "s": "NYSE:BAC/PC",
        "f": [
          "empty symbol"
        ]
      },
      {
        "s": "NYSE:BAC/PE",
        "f": [
          "empty symbol"
        ]
      },
      {
        "s": "NYSE:BAC/PK",
        "f": [
          "empty symbol"
        ]
      },
      {
        "s": "NYSE:BAC/PL",
        "f": [
          "empty symbol"
        ]
      },
      {
        "s": "NYSE:BAC/PW",
        "f": [
          "empty symbol"
        ]
      },
      {
        "s": "NYSE:BAC/PY",
        "f": [
          "empty symbol"
        ]
      },
      {
        "s": "NYSE:BAH",
        "f": [
          "empty symbol"
        ]
      },
      {
        "s": "NYSE:BAK",
        "f": [
          "empty symbol"
        ]
      },
      {
        "s": "NYSE:BAM",
        "f": [
          "empty symbol"
        ]
      },
      {
        "s": "NYSE:BAP",
        "f": [
          "empty symbol"
        ]
      },
      {
        "s": "NYSE:BAS",
        "f": [
          "empty symbol"
        ]
      },
      {
        "s": "NYSE:BAX",
        "f": [
          "empty symbol"
        ]
      },
      {
        "s": "NYSE:BCEI",
        "f": [
          "empty symbol"
        ]
      },
      {
        "s": "NYSE:BCRH",
        "f": [
          "empty symbol"
        ]
      },
      {
        "s": "NYSE:BERY",
        "f": [
          "empty symbol"
        ]
      },
      {
        "s": "NYSE:BFAM",
        "f": [
          "empty symbol"
        ]
      },
      {
        "s": "NYSE:BFS/PC",
        "f": [
          "empty symbol"
        ]
      },
      {
        "s": "NYSE:BFS/PD",
        "f": [
          "empty symbol"
        ]
      },
      {
        "s": "NYSE:BH.A",
        "f": [
          "empty symbol"
        ]
      },
      {
        "s": "NYSE:BHGE",
        "f": [
          "empty symbol"
        ]
      },
      {
        "s": "NYSE:BIO.B",
        "f": [
          "empty symbol"
        ]
      },
      {
        "s": "NYSE:BIT",
        "f": [
          "empty symbol"
        ]
      },
      {
        "s": "NYSE:BITA",
        "f": [
          "empty symbol"
        ]
      },
      {
        "s": "NYSE:BK/PC",
        "f": [
          "empty symbol"
        ]
      },
      {
        "s": "NYSE:BMA",
        "f": [
          "empty symbol"
        ]
      },
      {
        "s": "NYSE:BNED",
        "f": [
          "empty symbol"
        ]
      },
      {
        "s": "NYSE:BPMP",
        "f": [
          "empty symbol"
        ]
      },
      {
        "s": "NYSE:BRK.A",
        "f": [
          "empty symbol"
        ]
      },
      {
        "s": "NYSE:BRK.B",
        "f": [
          "empty symbol"
        ]
      },
      {
        "s": "NYSE:BRSS",
        "f": [
          "empty symbol"
        ]
      },
      {
        "s": "NYSE:CAI/PB",
        "f": [
          "empty symbol"
        ]
      },
      {
        "s": "NYSE:CBB/PB",
        "f": [
          "empty symbol"
        ]
      },
      {
        "s": "NYSE:CBRE",
        "f": [
          "empty symbol"
        ]
      },
      {
        "s": "NYSE:CBS.A",
        "f": [
          "empty symbol"
        ]
      },
      {
        "s": "NYSE:CEE",
        "f": [
          "empty symbol"
        ]
      },
      {
        "s": "NYSE:CFXA",
        "f": [
          "empty symbol"
        ]
      },
      {
        "s": "NYSE:CHE",
        "f": [
          "empty symbol"
        ]
      },
      {
        "s": "NYSE:CHH",
        "f": [
          "empty symbol"
        ]
      },
      {
        "s": "NYSE:CHK",
        "f": [
          "empty symbol"
        ]
      },
      {
        "s": "NYSE:CHMI",
        "f": [
          "empty symbol"
        ]
      },
      {
        "s": "NYSE:CHN",
        "f": [
          "empty symbol"
        ]
      },
      {
        "s": "NYSE:CHRA",
        "f": [
          "empty symbol"
        ]
      },
      {
        "s": "NYSE:CHS",
        "f": [
          "empty symbol"
        ]
      },
      {
        "s": "NYSE:CHSP",
        "f": [
          "empty symbol"
        ]
      },
      {
        "s": "NYSE:CHT",
        "f": [
          "empty symbol"
        ]
      },
      {
        "s": "NYSE:CHU",
        "f": [
          "empty symbol"
        ]
      },
      {
        "s": "NYSE:CIA",
        "f": [
          "empty symbol"
        ]
      },
      {
        "s": "NYSE:CIC.U",
        "f": [
          "empty symbol"
        ]
      },
      {
        "s": "NYSE:CIEN",
        "f": [
          "empty symbol"
        ]
      },
      {
        "s": "NYSE:CIG.C",
        "f": [
          "empty symbol"
        ]
      },
      {
        "s": "NYSE:CIM/PA",
        "f": [
          "empty symbol"
        ]
      },
      {
        "s": "NYSE:CIM/PB",
        "f": [
          "empty symbol"
        ]
      },
      {
        "s": "NYSE:CIM/PC",
        "f": [
          "empty symbol"
        ]
      },
      {
        "s": "NYSE:CIM/PD",
        "f": [
          "empty symbol"
        ]
      },
      {
        "s": "NYSE:CIO",
        "f": [
          "empty symbol"
        ]
      },
      {
        "s": "NYSE:CIO/PA",
        "f": [
          "empty symbol"
        ]
      },
      {
        "s": "NYSE:CIR",
        "f": [
          "empty symbol"
        ]
      },
      {
        "s": "NYSE:CIT",
        "f": [
          "empty symbol"
        ]
      },
      {
        "s": "NYSE:CIVI",
        "f": [
          "no longer trading"
        ]
      },
      {
        "s": "NYSE:CKH",
        "f": [
          "empty symbol"
        ]
      },
      {
        "s": "NYSE:CLB",
        "f": [
          "empty symbol"
        ]
      },
      {
        "s": "NYSE:CLH",
        "f": [
          "empty symbol"
        ]
      },
      {
        "s": "NYSE:CLI",
        "f": [
          "empty symbol"
        ]
      },
      {
        "s": "NYSE:CLR",
        "f": [
          "empty symbol"
        ]
      },
      {
        "s": "NYSE:CLS",
        "f": [
          "empty symbol"
        ]
      },
      {
        "s": "NYSE:CLW",
        "f": [
          "empty symbol"
        ]
      },
      {
        "s": "NYSE:CLX",
        "f": [
          "empty symbol"
        ]
      },
      {
        "s": "NYSE:CMA",
        "f": [
          "empty symbol"
        ]
      },
      {
        "s": "NYSE:CMC",
        "f": [
          "empty symbol"
        ]
      },
      {
        "s": "NYSE:CMCM",
        "f": [
          "empty symbol"
        ]
      },
      {
        "s": "NYSE:CMG",
        "f": [
          "empty symbol"
        ]
      },
      {
        "s": "NYSE:CMI",
        "f": [
          "empty symbol"
        ]
      },
      {
        "s": "NYSE:CMO/PE",
        "f": [
          "empty symbol"
        ]
      },
      {
        "s": "NYSE:CMP",
        "f": [
          "empty symbol"
        ]
      },
      {
        "s": "NYSE:CMS/PB",
        "f": [
          "empty symbol"
        ]
      },
      {
        "s": "NYSE:CNA",
        "f": [
          "empty symbol"
        ]
      },
      {
        "s": "NYSE:CNC",
        "f": [
          "empty symbol"
        ]
      },
      {
        "s": "NYSE:CNF",
        "f": [
          "empty symbol"
        ]
      },
      {
        "s": "NYSE:CNI",
        "f": [
          "empty symbol"
        ]
      },
      {
        "s": "NYSE:CNK",
        "f": [
          "empty symbol"
        ]
      },
      {
        "s": "NYSE:CNO",
        "f": [
          "empty symbol"
        ]
      },
      {
        "s": "NYSE:CNP",
        "f": [
          "empty symbol"
        ]
      },
      {
        "s": "NYSE:CNP/PB",
        "f": [
          "empty symbol"
        ]
      },
      {
        "s": "NYSE:CNQ",
        "f": [
          "empty symbol"
        ]
      },
      {
        "s": "NYSE:CNS",
        "f": [
          "empty symbol"
        ]
      },
      {
        "s": "NYSE:CNX",
        "f": [
          "empty symbol"
        ]
      },
      {
        "s": "NYSE:CNXM",
        "f": [
          "empty symbol"
        ]
      },
      {
        "s": "NYSE:CODI/PA",
        "f": [
          "empty symbol"
        ]
      },
      {
        "s": "NYSE:CODI/PB",
        "f": [
          "empty symbol"
        ]
      },
      {
        "s": "NYSE:COE",
        "f": [
          "empty symbol"
        ]
      },
      {
        "s": "NYSE:COF/PC",
        "f": [
          "empty symbol"
        ]
      },
      {
        "s": "NYSE:COF/PD",
        "f": [
          "empty symbol"
        ]
      },
      {
        "s": "NYSE:COF/PF",
        "f": [
          "empty symbol"
        ]
      },
      {
        "s": "NYSE:COF/PH",
        "f": [
          "empty symbol"
        ]
      },
      {
        "s": "NYSE:COF/PP",
        "f": [
          "empty symbol"
        ]
      },
      {
        "s": "NYSE:COG",
        "f": [
          "empty symbol"
        ]
      },
      {
        "s": "NYSE:COLD",
        "f": [
          "empty symbol"
        ]
      },
      {
        "s": "NYSE:COO",
        "f": [
          "empty symbol"
        ]
      },
      {
        "s": "NYSE:COP",
        "f": [
          "empty symbol"
        ]
      },
      {
        "s": "NYSE:COR",
        "f": [
          "empty symbol"
        ]
      },
      {
        "s": "NYSE:CORR",
        "f": [
          "empty symbol"
        ]
      },
      {
        "s": "NYSE:CORR/PA",
        "f": [
          "empty symbol"
        ]
      },
      {
        "s": "NYSE:COT",
        "f": [
          "empty symbol"
        ]
      },
      {
        "s": "NYSE:COTY",
        "f": [
          "empty symbol"
        ]
      },
      {
        "s": "NYSE:CPA",
        "f": [
          "empty symbol"
        ]
      },
      {
        "s": "NYSE:CPB",
        "f": [
          "empty symbol"
        ]
      },
      {
        "s": "NYSE:CPE",
        "f": [
          "empty symbol"
        ]
      },
      {
        "s": "NYSE:CPE/PA",
        "f": [
          "empty symbol"
        ]
      },
      {
        "s": "NYSE:CPF",
        "f": [
          "empty symbol"
        ]
      },
      {
        "s": "NYSE:CPG",
        "f": [
          "empty symbol"
        ]
      },
      {
        "s": "NYSE:CPK",
        "f": [
          "empty symbol"
        ]
      },
      {
        "s": "NYSE:CPL",
        "f": [
          "empty symbol"
        ]
      },
      {
        "s": "NYSE:CPS",
        "f": [
          "empty symbol"
        ]
      },
      {
        "s": "NYSE:CPT",
        "f": [
          "empty symbol"
        ]
      },
      {
        "s": "NYSE:CRH",
        "f": [
          "empty symbol"
        ]
      },
      {
        "s": "NYSE:CRI",
        "f": [
          "empty symbol"
        ]
      },
      {
        "s": "NYSE:CRK",
        "f": [
          "empty symbol"
        ]
      },
      {
        "s": "NYSE:CRL",
        "f": [
          "empty symbol"
        ]
      },
      {
        "s": "NYSE:CRM",
        "f": [
          "empty symbol"
        ]
      },
      {
        "s": "NYSE:CRR",
        "f": [
          "empty symbol"
        ]
      },
      {
        "s": "NYSE:CRS",
        "f": [
          "empty symbol"
        ]
      },
      {
        "s": "NYSE:CRY",
        "f": [
          "empty symbol"
        ]
      },
      {
        "s": "NYSE:CSL",
        "f": [
          "empty symbol"
        ]
      },
      {
        "s": "NYSE:CSLT",
        "f": [
          "empty symbol"
        ]
      },
      {
        "s": "NYSE:CSS",
        "f": [
          "empty symbol"
        ]
      },
      {
        "s": "NYSE:CSTM",
        "f": [
          "empty symbol"
        ]
      },
      {
        "s": "NYSE:CSU",
        "f": [
          "empty symbol"
        ]
      },
      {
        "s": "NYSE:CSV",
        "f": [
          "empty symbol"
        ]
      },
      {
        "s": "NYSE:CTL",
        "f": [
          "empty symbol"
        ]
      },
      {
        "s": "NYSE:CTS",
        "f": [
          "empty symbol"
        ]
      },
      {
        "s": "NYSE:CTT",
        "f": [
          "empty symbol"
        ]
      },
      {
        "s": "NYSE:CTY",
        "f": [
          "empty symbol"
        ]
      },
      {
        "s": "NYSE:CUB",
        "f": [
          "empty symbol"
        ]
      },
      {
        "s": "NYSE:CULP",
        "f": [
          "empty symbol"
        ]
      },
      {
        "s": "NYSE:CURO",
        "f": [
          "empty symbol"
        ]
      },
      {
        "s": "NYSE:CVA",
        "f": [
          "empty symbol"
        ]
      },
      {
        "s": "NYSE:CVE",
        "f": [
          "empty symbol"
        ]
      },
      {
        "s": "NYSE:CVI",
        "f": [
          "empty symbol"
        ]
      },
      {
        "s": "NYSE:CVS",
        "f": [
          "empty symbol"
        ]
      },
      {
        "s": "NYSE:CVX",
        "f": [
          "empty symbol"
        ]
      },
      {
        "s": "NYSE:CWH",
        "f": [
          "empty symbol"
        ]
      },
      {
        "s": "NYSE:CWK",
        "f": [
          "empty symbol"
        ]
      },
      {
        "s": "NYSE:CWT",
        "f": [
          "empty symbol"
        ]
      },
      {
        "s": "NYSE:CXE",
        "f": [
          "empty symbol"
        ]
      },
      {
        "s": "NYSE:CXH",
        "f": [
          "empty symbol"
        ]
      },
      {
        "s": "NYSE:CXO",
        "f": [
          "empty symbol"
        ]
      },
      {
        "s": "NYSE:CXP",
        "f": [
          "empty symbol"
        ]
      },
      {
        "s": "NYSE:CYD",
        "f": [
          "empty symbol"
        ]
      },
      {
        "s": "NYSE:CYH",
        "f": [
          "empty symbol"
        ]
      },
      {
        "s": "NYSE:CZZ",
        "f": [
          "empty symbol"
        ]
      },
      {
        "s": "NYSE:DAC",
        "f": [
          "empty symbol"
        ]
      },
      {
        "s": "NYSE:DAL",
        "f": [
          "empty symbol"
        ]
      },
      {
        "s": "NYSE:DAN",
        "f": [
          "empty symbol"
        ]
      },
      {
        "s": "NYSE:DAR",
        "f": [
          "empty symbol"
        ]
      },
      {
        "s": "NYSE:DATA",
        "f": [
          "empty symbol"
        ]
      },
      {
        "s": "NYSE:DAVA",
        "f": [
          "empty symbol"
        ]
      },
      {
        "s": "NYSE:DBD",
        "f": [
          "empty symbol"
        ]
      },
      {
        "s": "NYSE:DBI",
        "f": [
          "empty symbol"
        ]
      },
      {
        "s": "NYSE:DBL",
        "f": [
          "empty symbol"
        ]
      },
      {
        "s": "NYSE:DCF",
        "f": [
          "empty symbol"
        ]
      },
      {
        "s": "NYSE:DCI",
        "f": [
          "empty symbol"
        ]
      },
      {
        "s": "NYSE:DCO",
        "f": [
          "empty symbol"
        ]
      },
      {
        "s": "NYSE:DCP",
        "f": [
          "empty symbol"
        ]
      },
      {
        "s": "NYSE:DCP/PB",
        "f": [
          "empty symbol"
        ]
      },
      {
        "s": "NYSE:DCP/PC",
        "f": [
          "empty symbol"
        ]
      },
      {
        "s": "NYSE:DD/PA",
        "f": [
          "empty symbol"
        ]
      },
      {
        "s": "NYSE:DD/PB",
        "f": [
          "empty symbol"
        ]
      },
      {
        "s": "NYSE:DDD",
        "f": [
          "empty symbol"
        ]
      },
      {
        "s": "NYSE:DDF",
        "f": [
          "empty symbol"
        ]
      },
      {
        "s": "NYSE:DDT",
        "f": [
          "empty symbol"
        ]
      },
      {
        "s": "NYSE:DEA",
        "f": [
          "empty symbol"
        ]
      },
      {
        "s": "NYSE:DECK",
        "f": [
          "empty symbol"
        ]
      },
      {
        "s": "NYSE:DEI",
        "f": [
          "empty symbol"
        ]
      },
      {
        "s": "NYSE:DELL",
        "f": [
          "empty symbol"
        ]
      },
      {
        "s": "NYSE:DEO",
        "f": [
          "empty symbol"
        ]
      },
      {
        "s": "NYSE:DESP",
        "f": [
          "empty symbol"
        ]
      },
      {
        "s": "NYSE:DEX",
        "f": [
          "empty symbol"
        ]
      },
      {
        "s": "NYSE:DLR/PC",
        "f": [
          "empty symbol"
        ]
      },
      {
        "s": "NYSE:DLR/PG",
        "f": [
          "empty symbol"
        ]
      },
      {
        "s": "NYSE:DLR/PI",
        "f": [
          "empty symbol"
        ]
      },
      {
        "s": "NYSE:DLR/PJ",
        "f": [
          "empty symbol"
        ]
      },
      {
        "s": "NYSE:DLR/PK",
        "f": [
          "empty symbol"
        ]
      },
      {
        "s": "NYSE:DNOW",
        "f": [
          "empty symbol"
        ]
      },
      {
        "s": "NYSE:DPLO",
        "f": [
          "empty symbol"
        ]
      },
      {
        "s": "NYSE:DS/PB",
        "f": [
          "empty symbol"
        ]
      },
      {
        "s": "NYSE:DS/PC",
        "f": [
          "empty symbol"
        ]
      },
      {
        "s": "NYSE:DS/PD",
        "f": [
          "empty symbol"
        ]
      },
      {
        "s": "NYSE:E",
        "f": [
          "empty symbol"
        ]
      },
      {
        "s": "NYSE:EBR.B",
        "f": [
          "empty symbol"
        ]
      },
      {
        "s": "NYSE:EHC",
        "f": [
          "empty symbol"
        ]
      },
      {
        "s": "NYSE:EHI",
        "f": [
          "empty symbol"
        ]
      },
      {
        "s": "NYSE:EHT",
        "f": [
          "empty symbol"
        ]
      },
      {
        "s": "NYSE:EIG",
        "f": [
          "empty symbol"
        ]
      },
      {
        "s": "NYSE:EIX",
        "f": [
          "empty symbol"
        ]
      },
      {
        "s": "NYSE:ELF",
        "f": [
          "empty symbol"
        ]
      },
      {
        "s": "NYSE:ELJ",
        "f": [
          "empty symbol"
        ]
      },
      {
        "s": "NYSE:ELP",
        "f": [
          "empty symbol"
        ]
      },
      {
        "s": "NYSE:ELS",
        "f": [
          "empty symbol"
        ]
      },
      {
        "s": "NYSE:ELY",
        "f": [
          "empty symbol"
        ]
      },
      {
        "s": "NYSE:EPRT",
        "f": [
          "empty symbol"
        ]
      },
      {
        "s": "NYSE:ESL",
        "f": [
          "no longer trading"
        ]
      },
      {
        "s": "NYSE:F",
        "f": [
          "empty symbol"
        ]
      },
      {
        "s": "NYSE:FICO",
        "f": [
          "empty symbol"
        ]
      },
      {
        "s": "NYSE:FLC",
        "f": [
          "empty symbol"
        ]
      },
      {
        "s": "NYSE:FLR",
        "f": [
          "empty symbol"
        ]
      },
      {
        "s": "NYSE:FLS",
        "f": [
          "empty symbol"
        ]
      },
      {
        "s": "NYSE:FLT",
        "f": [
          "empty symbol"
        ]
      },
      {
        "s": "NYSE:FLY",
        "f": [
          "empty symbol"
        ]
      },
      {
        "s": "NYSE:FMC",
        "f": [
          "empty symbol"
        ]
      },
      {
        "s": "NYSE:FMN",
        "f": [
          "empty symbol"
        ]
      },
      {
        "s": "NYSE:FMO",
        "f": [
          "empty symbol"
        ]
      },
      {
        "s": "NYSE:FMS",
        "f": [
          "empty symbol"
        ]
      },
      {
        "s": "NYSE:FMX",
        "f": [
          "empty symbol"
        ]
      },
      {
        "s": "NYSE:FMY",
        "f": [
          "empty symbol"
        ]
      },
      {
        "s": "NYSE:FNB",
        "f": [
          "empty symbol"
        ]
      },
      {
        "s": "NYSE:FNB/PE",
        "f": [
          "empty symbol"
        ]
      },
      {
        "s": "NYSE:FNF",
        "f": [
          "empty symbol"
        ]
      },
      {
        "s": "NYSE:FNV",
        "f": [
          "empty symbol"
        ]
      },
      {
        "s": "NYSE:G",
        "f": [
          "empty symbol"
        ]
      },
      {
        "s": "NYSE:GGT/PB",
        "f": [
          "empty symbol"
        ]
      },
      {
        "s": "NYSE:GGT/PE",
        "f": [
          "empty symbol"
        ]
      },
      {
        "s": "NYSE:GIG.U",
        "f": [
          "no longer trading"
        ]
      },
      {
        "s": "NYSE:GLP",
        "f": [
          "empty symbol"
        ]
      },
      {
        "s": "NYSE:GLT",
        "f": [
          "empty symbol"
        ]
      },
      {
        "s": "NYSE:GME",
        "f": [
          "empty symbol"
        ]
      },
      {
        "s": "NYSE:GMED",
        "f": [
          "empty symbol"
        ]
      },
      {
        "s": "NYSE:GMRE/PA",
        "f": [
          "empty symbol"
        ]
      },
      {
        "s": "NYSE:GMS",
        "f": [
          "empty symbol"
        ]
      },
      {
        "s": "NYSE:GMZ",
        "f": [
          "empty symbol"
        ]
      },
      {
        "s": "NYSE:GNC",
        "f": [
          "empty symbol"
        ]
      },
      {
        "s": "NYSE:GNE",
        "f": [
          "empty symbol"
        ]
      },
      {
        "s": "NYSE:GNK",
        "f": [
          "empty symbol"
        ]
      },
      {
        "s": "NYSE:GNL",
        "f": [
          "empty symbol"
        ]
      },
      {
        "s": "NYSE:GNT",
        "f": [
          "empty symbol"
        ]
      },
      {
        "s": "NYSE:GNW",
        "f": [
          "empty symbol"
        ]
      },
      {
        "s": "NYSE:GOF",
        "f": [
          "empty symbol"
        ]
      },
      {
        "s": "NYSE:GOL",
        "f": [
          "empty symbol"
        ]
      },
      {
        "s": "NYSE:GOLD",
        "f": [
          "empty symbol"
        ]
      },
      {
        "s": "NYSE:GPC",
        "f": [
          "empty symbol"
        ]
      },
      {
        "s": "NYSE:GPI",
        "f": [
          "empty symbol"
        ]
      },
      {
        "s": "NYSE:GPK",
        "f": [
          "empty symbol"
        ]
      },
      {
        "s": "NYSE:GPM",
        "f": [
          "empty symbol"
        ]
      },
      {
        "s": "NYSE:GPMT",
        "f": [
          "empty symbol"
        ]
      },
      {
        "s": "NYSE:GPN",
        "f": [
          "empty symbol"
        ]
      },
      {
        "s": "NYSE:GPS",
        "f": [
          "empty symbol"
        ]
      },
      {
        "s": "NYSE:GPX",
        "f": [
          "empty symbol"
        ]
      },
      {
        "s": "NYSE:H",
        "f": [
          "empty symbol"
        ]
      },
      {
        "s": "NYSE:HESM",
        "f": [
          "empty symbol"
        ]
      },
      {
        "s": "NYSE:HNGR",
        "f": [
          "empty symbol"
        ]
      },
      {
        "s": "NYSE:HOG",
        "f": [
          "empty symbol"
        ]
      },
      {
        "s": "NYSE:HON",
        "f": [
          "empty symbol"
        ]
      },
      {
        "s": "NYSE:HOS",
        "f": [
          "empty symbol"
        ]
      },
      {
        "s": "NYSE:HOV",
        "f": [
          "empty symbol"
        ]
      },
      {
        "s": "NYSE:HPE",
        "f": [
          "empty symbol"
        ]
      },
      {
        "s": "NYSE:HPI",
        "f": [
          "empty symbol"
        ]
      },
      {
        "s": "NYSE:HPP",
        "f": [
          "empty symbol"
        ]
      },
      {
        "s": "NYSE:HPQ",
        "f": [
          "empty symbol"
        ]
      },
      {
        "s": "NYSE:HPR",
        "f": [
          "empty symbol"
        ]
      },
      {
        "s": "NYSE:HPS",
        "f": [
          "empty symbol"
        ]
      },
      {
        "s": "NYSE:HQH",
        "f": [
          "empty symbol"
        ]
      },
      {
        "s": "NYSE:HQL",
        "f": [
          "empty symbol"
        ]
      },
      {
        "s": "NYSE:HRB",
        "f": [
          "empty symbol"
        ]
      },
      {
        "s": "NYSE:HRC",
        "f": [
          "empty symbol"
        ]
      },
      {
        "s": "NYSE:HRI",
        "f": [
          "empty symbol"
        ]
      },
      {
        "s": "NYSE:HRL",
        "f": [
          "empty symbol"
        ]
      },
      {
        "s": "NYSE:HRS",
        "f": [
          "empty symbol"
        ]
      },
      {
        "s": "NYSE:I",
        "f": [
          "empty symbol"
        ]
      },
      {
        "s": "NYSE:IMAX",
        "f": [
          "empty symbol"
        ]
      },
      {
        "s": "NYSE:IPG",
        "f": [
          "empty symbol"
        ]
      },
      {
        "s": "NYSE:IPHI",
        "f": [
          "empty symbol"
        ]
      },
      {
        "s": "NYSE:IPI",
        "f": [
          "empty symbol"
        ]
      },
      {
        "s": "NYSE:IPOA",
        "f": [
          "empty symbol"
        ]
      },
      {
        "s": "NYSE:IPSC",
        "f": [
          "empty symbol"
        ]
      },
      {
        "s": "NYSE:IQI",
        "f": [
          "empty symbol"
        ]
      },
      {
        "s": "NYSE:IQV",
        "f": [
          "empty symbol"
        ]
      },
      {
        "s": "NYSE:IRL",
        "f": [
          "empty symbol"
        ]
      },
      {
        "s": "NYSE:IRM",
        "f": [
          "empty symbol"
        ]
      },
      {
        "s": "NYSE:IRR",
        "f": [
          "empty symbol"
        ]
      },
      {
        "s": "NYSE:IRS",
        "f": [
          "empty symbol"
        ]
      },
      {
        "s": "NYSE:IRT",
        "f": [
          "empty symbol"
        ]
      },
      {
        "s": "NYSE:ISD",
        "f": [
          "empty symbol"
        ]
      },
      {
        "s": "NYSE:ISG",
        "f": [
          "empty symbol"
        ]
      },
      {
        "s": "NYSE:ITT",
        "f": [
          "empty symbol"
        ]
      },
      {
        "s": "NYSE:ITW",
        "f": [
          "empty symbol"
        ]
      },
      {
        "s": "NYSE:JBGS",
        "f": [
          "empty symbol"
        ]
      },
      {
        "s": "NYSE:JEMD",
        "f": [
          "empty symbol"
        ]
      },
      {
        "s": "NYSE:JRI",
        "f": [
          "empty symbol"
        ]
      },
      {
        "s": "NYSE:JRO",
        "f": [
          "empty symbol"
        ]
      },
      {
        "s": "NYSE:JRS",
        "f": [
          "empty symbol"
        ]
      },
      {
        "s": "NYSE:JSD",
        "f": [
          "empty symbol"
        ]
      },
      {
        "s": "NYSE:JTA",
        "f": [
          "empty symbol"
        ]
      },
      {
        "s": "NYSE:JTD",
        "f": [
          "empty symbol"
        ]
      },
      {
        "s": "NYSE:MNRL",
        "f": [
          "no longer trading"
        ]
      },
      {
        "s": "NYSE:MTB/P",
        "f": [
          "no longer trading"
        ]
      },
      {
        "s": "NYSE:MTB/PC",
        "f": [
          "no longer trading"
        ]
      },
      {
        "s": "NYSE:NAV/PD",
        "f": [
          "no longer trading"
        ]
      },
      {
        "s": "NYSE:PINS",
        "f": [
          "no longer trading"
        ]
      },
      {
        "s": "NYSE:REN",
        "f": [
          "empty symbol"
        ]
      },
      {
        "s": "NYSE:USB/PP",
        "f": [
          "empty symbol"
        ]
      },
      {
        "s": "NYSE:VHI",
        "f": [
          "empty symbol"
        ]
      },
      {
        "s": "NYSE:WIA",
        "f": [
          "empty symbol"
        ]
      },
      {
        "s": "OTC:ACAN",
        "f": [
          "empty symbol"
        ]
      },
      {
        "s": "OTC:ADHG",
        "f": [
          "no longer trading"
        ]
      },
      {
        "s": "OTC:AERGP",
        "f": [
          "empty symbol"
        ]
      },
      {
        "s": "OTC:AKOM",
        "f": [
          "no longer trading"
        ]
      },
      {
        "s": "OTC:ALTPF",
        "f": [
          "no longer trading"
        ]
      },
      {
        "s": "OTC:ANPOF",
        "f": [
          "no longer trading"
        ]
      },
      {
        "s": "OTC:ANTGF",
        "f": [
          "no longer trading"
        ]
      },
      {
        "s": "OTC:ASCMB",
        "f": [
          "no longer trading"
        ]
      },
      {
        "s": "OTC:ASFT",
        "f": [
          "no longer trading"
        ]
      },
      {
        "s": "OTC:ATXG",
        "f": [
          "no longer trading"
        ]
      },
      {
        "s": "OTC:AVMR",
        "f": [
          "no longer trading"
        ]
      },
      {
        "s": "OTC:BATRB",
        "f": [
          "no longer trading"
        ]
      },
      {
        "s": "OTC:BBLG",
        "f": [
          "no longer trading"
        ]
      },
      {
        "s": "OTC:CHGH",
        "f": [
          "no longer trading"
        ]
      },
      {
        "s": "OTC:CHNUF",
        "f": [
          "no longer trading"
        ]
      },
      {
        "s": "OTC:CMGGF",
        "f": [
          "no longer trading"
        ]
      },
      {
        "s": "OTC:CNENF",
        "f": [
          "no longer trading"
        ]
      },
      {
        "s": "OTC:CNIGO",
        "f": [
          "no longer trading"
        ]
      },
      {
        "s": "OTC:CNMF",
        "f": [
          "no longer trading"
        ]
      },
      {
        "s": "OTC:CORX",
        "f": [
          "no longer trading"
        ]
      },
      {
        "s": "OTC:COSO",
        "f": [
          "no longer trading"
        ]
      },
      {
        "s": "OTC:DCNNF",
        "f": [
          "no longer trading"
        ]
      },
      {
        "s": "OTC:DMKBB",
        "f": [
          "no longer trading"
        ]
      },
      {
        "s": "OTC:DREM",
        "f": [
          "no longer trading"
        ]
      },
      {
        "s": "OTC:DUUO",
        "f": [
          "no longer trading"
        ]
      },
      {
        "s": "OTC:DYMEF",
        "f": [
          "empty symbol"
        ]
      },
      {
        "s": "OTC:ELXMY",
        "f": [
          "no longer trading"
        ]
      },
      {
        "s": "OTC:EOSS",
        "f": [
          "no longer trading"
        ]
      },
      {
        "s": "OTC:EPWMF",
        "f": [
          "no longer trading"
        ]
      },
      {
        "s": "OTC:EWCLF",
        "f": [
          "no longer trading"
        ]
      },
      {
        "s": "OTC:EWLU",
        "f": [
          "no longer trading"
        ]
      },
      {
        "s": "OTC:FBPA",
        "f": [
          "no longer trading"
        ]
      },
      {
        "s": "OTC:FGNV",
        "f": [
          "no longer trading"
        ]
      },
      {
        "s": "OTC:FLLZ",
        "f": [
          "no longer trading"
        ]
      },
      {
        "s": "OTC:FOSI",
        "f": [
          "no longer trading"
        ]
      },
      {
        "s": "OTC:FREGP",
        "f": [
          "no longer trading"
        ]
      },
      {
        "s": "OTC:FSNT",
        "f": [
          "no longer trading"
        ]
      },
      {
        "s": "OTC:FVVSF",
        "f": [
          "no longer trading"
        ]
      },
      {
        "s": "OTC:GFKSY",
        "f": [
          "no longer trading"
        ]
      },
      {
        "s": "OTC:GLNS",
        "f": [
          "no longer trading"
        ]
      },
      {
        "s": "OTC:GOCOF",
        "f": [
          "no longer trading"
        ]
      },
      {
        "s": "OTC:GOTRF",
        "f": [
          "no longer trading"
        ]
      },
      {
        "s": "OTC:GPVRF",
        "f": [
          "empty symbol"
        ]
      },
      {
        "s": "OTC:GRRBP",
        "f": [
          "no longer trading"
        ]
      },
      {
        "s": "OTC:GTVI",
        "f": [
          "no longer trading"
        ]
      },
      {
        "s": "OTC:GZDIF",
        "f": [
          "no longer trading"
        ]
      },
      {
        "s": "OTC:HHHEF",
        "f": [
          "no longer trading"
        ]
      },
      {
        "s": "OTC:HOILF",
        "f": [
          "no longer trading"
        ]
      },
      {
        "s": "OTC:HQDA",
        "f": [
          "no longer trading"
        ]
      },
      {
        "s": "OTC:HYAS",
        "f": [
          "no longer trading"
        ]
      },
      {
        "s": "OTC:HZNFF",
        "f": [
          "no longer trading"
        ]
      },
      {
        "s": "OTC:IESFY",
        "f": [
          "no longer trading"
        ]
      },
      {
        "s": "OTC:ILAL",
        "f": [
          "empty symbol"
        ]
      },
      {
        "s": "OTC:ILCC",
        "f": [
          "no longer trading"
        ]
      },
      {
        "s": "OTC:IMGL",
        "f": [
          "no longer trading"
        ]
      },
      {
        "s": "OTC:IPNFF",
        "f": [
          "no longer trading"
        ]
      },
      {
        "s": "OTC:ISRJF",
        "f": [
          "no longer trading"
        ]
      },
      {
        "s": "OTC:IWBB",
        "f": [
          "no longer trading"
        ]
      },
      {
        "s": "OTC:JADG",
        "f": [
          "no longer trading"
        ]
      },
      {
        "s": "OTC:JKRO",
        "f": [
          "no longer trading"
        ]
      },
      {
        "s": "OTC:KBPH",
        "f": [
          "no longer trading"
        ]
      },
      {
        "s": "OTC:LBCMF",
        "f": [
          "no longer trading"
        ]
      },
      {
        "s": "OTC:LBRDB",
        "f": [
          "no longer trading"
        ]
      },
      {
        "s": "OTC:LEAI",
        "f": [
          "no longer trading"
        ]
      },
      {
        "s": "OTC:MAMP",
        "f": [
          "no longer trading"
        ]
      },
      {
        "s": "OTC:MCBS",
        "f": [
          "no longer trading"
        ]
      },
      {
        "s": "OTC:MCCX",
        "f": [
          "no longer trading"
        ]
      },
      {
        "s": "OTC:MCVT",
        "f": [
          "no longer trading"
        ]
      },
      {
        "s": "OTC:MDEX",
        "f": [
          "no longer trading"
        ]
      },
      {
        "s": "OTC:MHDG",
        "f": [
          "no longer trading"
        ]
      },
      {
        "s": "OTC:MLGCD",
        "f": [
          "no longer trading"
        ]
      },
      {
        "s": "OTC:MMND",
        "f": [
          "no longer trading"
        ]
      },
      {
        "s": "OTC:MNBO",
        "f": [
          "no longer trading"
        ]
      },
      {
        "s": "OTC:MOBIF",
        "f": [
          "no longer trading"
        ]
      },
      {
        "s": "OTC:MOST",
        "f": [
          "no longer trading"
        ]
      },
      {
        "s": "OTC:MRNTY",
        "f": [
          "no longer trading"
        ]
      },
      {
        "s": "OTC:NAHD",
        "f": [
          "no longer trading"
        ]
      },
      {
        "s": "OTC:NQMLF",
        "f": [
          "no longer trading"
        ]
      },
      {
        "s": "OTC:NTOX",
        "f": [
          "no longer trading"
        ]
      },
      {
        "s": "OTC:NUZE",
        "f": [
          "no longer trading"
        ]
      },
      {
        "s": "OTC:NVMMP",
        "f": [
          "no longer trading"
        ]
      },
      {
        "s": "OTC:OCNSF",
        "f": [
          "no longer trading"
        ]
      },
      {
        "s": "OTC:PACQF",
        "f": [
          "no longer trading"
        ]
      },
      {
        "s": "OTC:PBSV",
        "f": [
          "no longer trading"
        ]
      },
      {
        "s": "OTC:PEMSF",
        "f": [
          "no longer trading"
        ]
      },
      {
        "s": "OTC:PGMLF",
        "f": [
          "no longer trading"
        ]
      },
      {
        "s": "OTC:PMHG",
        "f": [
          "no longer trading"
        ]
      },
      {
        "s": "OTC:PRIEF",
        "f": [
          "empty symbol"
        ]
      },
      {
        "s": "OTC:PTEO",
        "f": [
          "no longer trading"
        ]
      },
      {
        "s": "OTC:PTIX",
        "f": [
          "no longer trading"
        ]
      },
      {
        "s": "OTC:PVOTF",
        "f": [
          "empty symbol"
        ]
      },
      {
        "s": "OTC:RASP",
        "f": [
          "no longer trading"
        ]
      },
      {
        "s": "OTC:RIGMF",
        "f": [
          "no longer trading"
        ]
      },
      {
        "s": "OTC:ROIUF",
        "f": [
          "no longer trading"
        ]
      },
      {
        "s": "OTC:RPNRF",
        "f": [
          "no longer trading"
        ]
      },
      {
        "s": "OTC:SEGN",
        "f": [
          "no longer trading"
        ]
      },
      {
        "s": "OTC:SGBI",
        "f": [
          "no longer trading"
        ]
      },
      {
        "s": "OTC:SRUXY",
        "f": [
          "empty symbol"
        ]
      },
      {
        "s": "OTC:STCB",
        "f": [
          "no longer trading"
        ]
      },
      {
        "s": "OTC:STXMF",
        "f": [
          "no longer trading"
        ]
      },
      {
        "s": "OTC:SVYSF",
        "f": [
          "no longer trading"
        ]
      },
      {
        "s": "OTC:SWGI",
        "f": [
          "no longer trading"
        ]
      },
      {
        "s": "OTC:TAKD",
        "f": [
          "no longer trading"
        ]
      },
      {
        "s": "OTC:TDLAF",
        "f": [
          "no longer trading"
        ]
      },
      {
        "s": "OTC:TDNT",
        "f": [
          "no longer trading"
        ]
      },
      {
        "s": "OTC:TIMGF",
        "f": [
          "no longer trading"
        ]
      },
      {
        "s": "OTC:TKGBF",
        "f": [
          "no longer trading"
        ]
      },
      {
        "s": "OTC:TRRB",
        "f": [
          "no longer trading"
        ]
      },
      {
        "s": "OTC:TVTV",
        "f": [
          "empty symbol"
        ]
      },
      {
        "s": "OTC:TYCB",
        "f": [
          "no longer trading"
        ]
      },
      {
        "s": "OTC:URYL",
        "f": [
          "no longer trading"
        ]
      },
      {
        "s": "OTC:VCOR",
        "f": [
          "no longer trading"
        ]
      },
      {
        "s": "OTC:VGGOD",
        "f": [
          "no longer trading"
        ]
      },
      {
        "s": "OTC:VYEY",
        "f": [
          "no longer trading"
        ]
      },
      {
        "s": "OTC:WAYS",
        "f": [
          "no longer trading"
        ]
      },
      {
        "s": "OTC:WECFY",
        "f": [
          "no longer trading"
        ]
      },
      {
        "s": "OTC:ZADDD",
        "f": [
          "empty symbol"
        ]
      }
    ]
  }