{
    "black_list": [
      {
        "s": "SZSE:000008",
        "f": [
          "no longer trading"
        ]
      },
      {
        "s": "SZSE:000022",
        "f": [
          "no longer trading"
        ]
      },
      {
        "s": "SZSE:000029",
        "f": [
          "no longer trading"
        ]
      },
      {
        "s": "SZSE:000035",
        "f": [
          "no longer trading"
        ]
      },
      {
        "s": "SZSE:000038",
        "f": [
          "no longer trading"
        ]
      },
      {
        "s": "SZSE:000415",
        "f": [
          "no longer trading"
        ]
      },
      {
        "s": "SZSE:000426",
        "f": [
          "no longer trading"
        ]
      },
      {
        "s": "SZSE:000509",
        "f": [
          "no longer trading"
        ]
      },
      {
        "s": "SZSE:000526",
        "f": [
          "no longer trading"
        ]
      },
      {
        "s": "SZSE:000540",
        "f": [
          "no longer trading"
        ]
      },
      {
        "s": "SZSE:000545",
        "f": [
          "no longer trading"
        ]
      },
      {
        "s": "SZSE:000564",
        "f": [
          "no longer trading"
        ]
      },
      {
        "s": "SZSE:000566",
        "f": [
          "no longer trading"
        ]
      },
      {
        "s": "SZSE:000584",
        "f": [
          "no longer trading"
        ]
      },
      {
        "s": "SZSE:000603",
        "f": [
          "no longer trading"
        ]
      },
      {
        "s": "SZSE:000611",
        "f": [
          "no longer trading"
        ]
      },
      {
        "s": "SZSE:000616",
        "f": [
          "no longer trading"
        ]
      },
      {
        "s": "SZSE:000666",
        "f": [
          "no longer trading"
        ]
      },
      {
        "s": "SZSE:000669",
        "f": [
          "no longer trading"
        ]
      },
      {
        "s": "SZSE:000673",
        "f": [
          "no longer trading"
        ]
      },
      {
        "s": "SZSE:000693",
        "f": [
          "no longer trading"
        ]
      },
      {
        "s": "SZSE:000711",
        "f": [
          "no longer trading"
        ]
      },
      {
        "s": "SZSE:000723",
        "f": [
          "no longer trading"
        ]
      },
      {
        "s": "SZSE:000779",
        "f": [
          "no longer trading"
        ]
      },
      {
        "s": "SZSE:000793",
        "f": [
          "no longer trading"
        ]
      },
      {
        "s": "SZSE:000796",
        "f": [
          "no longer trading"
        ]
      },
      {
        "s": "SZSE:000825",
        "f": [
          "no longer trading"
        ]
      },
      {
        "s": "SZSE:000912",
        "f": [
          "no longer trading"
        ]
      },
      {
        "s": "SZSE:000967",
        "f": [
          "no longer trading"
        ]
      },
      {
        "s": "SZSE:000972",
        "f": [
          "no longer trading"
        ]
      },
      {
        "s": "SZSE:002011",
        "f": [
          "no longer trading"
        ]
      },
      {
        "s": "SZSE:002051",
        "f": [
          "no longer trading"
        ]
      },
      {
        "s": "SZSE:002053",
        "f": [
          "no longer trading"
        ]
      },
      {
        "s": "SZSE:002059",
        "f": [
          "no longer trading"
        ]
      },
      {
        "s": "SZSE:002075",
        "f": [
          "no longer trading"
        ]
      },
      {
        "s": "SZSE:002082",
        "f": [
          "no longer trading"
        ]
      },
      {
        "s": "SZSE:002086",
        "f": [
          "no longer trading"
        ]
      },
      {
        "s": "SZSE:002089",
        "f": [
          "no longer trading"
        ]
      },
      {
        "s": "SZSE:002098",
        "f": [
          "no longer trading"
        ]
      },
      {
        "s": "SZSE:002102",
        "f": [
          "no longer trading"
        ]
      },
      {
        "s": "SZSE:002113",
        "f": [
          "no longer trading"
        ]
      },
      {
        "s": "SZSE:002121",
        "f": [
          "no longer trading"
        ]
      },
      {
        "s": "SZSE:002143",
        "f": [
          "no longer trading"
        ]
      },
      {
        "s": "SZSE:002147",
        "f": [
          "no longer trading"
        ]
      },
      {
        "s": "SZSE:002171",
        "f": [
          "no longer trading"
        ]
      },
      {
        "s": "SZSE:002210",
        "f": [
          "no longer trading"
        ]
      },
      {
        "s": "SZSE:002226",
        "f": [
          "no longer trading"
        ]
      },
      {
        "s": "SZSE:002239",
        "f": [
          "no longer trading"
        ]
      },
      {
        "s": "SZSE:002252",
        "f": [
          "no longer trading"
        ]
      },
      {
        "s": "SZSE:002263",
        "f": [
          "no longer trading"
        ]
      },
      {
        "s": "SZSE:002301",
        "f": [
          "no longer trading"
        ]
      },
      {
        "s": "SZSE:002309",
        "f": [
          "no longer trading"
        ]
      },
      {
        "s": "SZSE:002310",
        "f": [
          "no longer trading"
        ]
      },
      {
        "s": "SZSE:002359",
        "f": [
          "no longer trading"
        ]
      },
      {
        "s": "SZSE:002369",
        "f": [
          "no longer trading"
        ]
      },
      {
        "s": "SZSE:002408",
        "f": [
          "no longer trading"
        ]
      },
      {
        "s": "SZSE:002411",
        "f": [
          "no longer trading"
        ]
      },
      {
        "s": "SZSE:002431",
        "f": [
          "no longer trading"
        ]
      },
      {
        "s": "SZSE:002436",
        "f": [
          "no longer trading"
        ]
      },
      {
        "s": "SZSE:002437",
        "f": [
          "no longer trading"
        ]
      },
      {
        "s": "SZSE:002445",
        "f": [
          "no longer trading"
        ]
      },
      {
        "s": "SZSE:002450",
        "f": [
          "no longer trading"
        ]
      },
      {
        "s": "SZSE:002464",
        "f": [
          "no longer trading"
        ]
      },
      {
        "s": "SZSE:002477",
        "f": [
          "no longer trading"
        ]
      },
      {
        "s": "SZSE:002485",
        "f": [
          "no longer trading"
        ]
      },
      {
        "s": "SZSE:002502",
        "f": [
          "no longer trading"
        ]
      },
      {
        "s": "SZSE:002512",
        "f": [
          "no longer trading"
        ]
      },
      {
        "s": "SZSE:002569",
        "f": [
          "no longer trading"
        ]
      },
      {
        "s": "SZSE:002573",
        "f": [
          "no longer trading"
        ]
      },
      {
        "s": "SZSE:002602",
        "f": [
          "no longer trading"
        ]
      },
      {
        "s": "SZSE:002610",
        "f": [
          "no longer trading"
        ]
      },
      {
        "s": "SZSE:002617",
        "f": [
          "no longer trading"
        ]
      },
      {
        "s": "SZSE:002630",
        "f": [
          "no longer trading"
        ]
      },
      {
        "s": "SZSE:002650",
        "f": [
          "no longer trading"
        ]
      },
      {
        "s": "SZSE:002656",
        "f": [
          "no longer trading"
        ]
      },
      {
        "s": "SZSE:002665",
        "f": [
          "no longer trading"
        ]
      },
      {
        "s": "SZSE:002668",
        "f": [
          "no longer trading"
        ]
      },
      {
        "s": "SZSE:002716",
        "f": [
          "no longer trading"
        ]
      },
      {
        "s": "SZSE:002719",
        "f": [
          "no longer trading"
        ]
      },
      {
        "s": "SZSE:002721",
        "f": [
          "no longer trading"
        ]
      },
      {
        "s": "SZSE:002723",
        "f": [
          "no longer trading"
        ]
      },
      {
        "s": "SZSE:002739",
        "f": [
          "no longer trading"
        ]
      },
      {
        "s": "SZSE:002778",
        "f": [
          "no longer trading"
        ]
      },
      {
        "s": "SZSE:002819",
        "f": [
          "no longer trading"
        ]
      },
      {
        "s": "SZSE:002856",
        "f": [
          "no longer trading"
        ]
      },
      {
        "s": "SZSE:140001",
        "f": [
          "empty symbol"
        ]
      },
      {
        "s": "SZSE:140002",
        "f": [
          "empty symbol"
        ]
      },
      {
        "s": "SZSE:140003",
        "f": [
          "empty symbol"
        ]
      },
      {
        "s": "SZSE:140004",
        "f": [
          "empty symbol"
        ]
      },
      {
        "s": "SZSE:140005",
        "f": [
          "empty symbol"
        ]
      },
      {
        "s": "SZSE:140006",
        "f": [
          "empty symbol",
          "test symbol"
        ]
      },
      {
        "s": "SZSE:200022",
        "f": [
          "no longer trading"
        ]
      },
      {
        "s": "SZSE:200029",
        "f": [
          "no longer trading"
        ]
      },
      {
        "s": "SZSE:300049",
        "f": [
          "no longer trading"
        ]
      },
      {
        "s": "SZSE:300072",
        "f": [
          "no longer trading"
        ]
      },
      {
        "s": "SZSE:300108",
        "f": [
          "no longer trading"
        ]
      },
      {
        "s": "SZSE:300111",
        "f": [
          "no longer trading"
        ]
      },
      {
        "s": "SZSE:300118",
        "f": [
          "no longer trading"
        ]
      },
      {
        "s": "SZSE:300131",
        "f": [
          "no longer trading"
        ]
      },
      {
        "s": "SZSE:300146",
        "f": [
          "no longer trading"
        ]
      },
      {
        "s": "SZSE:300187",
        "f": [
          "no longer trading"
        ]
      },
      {
        "s": "SZSE:300197",
        "f": [
          "no longer trading"
        ]
      },
      {
        "s": "SZSE:300198",
        "f": [
          "no longer trading"
        ]
      },
      {
        "s": "SZSE:300229",
        "f": [
          "no longer trading"
        ]
      },
      {
        "s": "SZSE:300238",
        "f": [
          "no longer trading"
        ]
      },
      {
        "s": "SZSE:300299",
        "f": [
          "no longer trading"
        ]
      },
      {
        "s": "SZSE:300324",
        "f": [
          "no longer trading"
        ]
      },
      {
        "s": "SZSE:300343",
        "f": [
          "no longer trading"
        ]
      },
      {
        "s": "SZSE:300350",
        "f": [
          "no longer trading"
        ]
      },
      {
        "s": "SZSE:300362",
        "f": [
          "no longer trading"
        ]
      },
      {
        "s": "SZSE:300464",
        "f": [
          "no longer trading"
        ]
      },
      {
        "s": "SZSE:300491",
        "f": [
          "no longer trading"
        ]
      },
      {
        "s": "SZSE:300510",
        "f": [
          "no longer trading"
        ]
      },
      {
        "s": "SZSE:300561",
        "f": [
          "no longer trading"
        ]
      },
      {
        "s": "SZSE:300586",
        "f": [
          "no longer trading"
        ]
      },
      {
        "s": "SZSE:300603",
        "f": [
          "no longer trading"
        ]
      },
      {
        "s": "SZSE:300670",
        "f": [
          "no longer trading"
        ]
      },
      {
        "s": "SZSE:300683",
        "f": [
          "no longer trading"
        ]
      },
      {
        "s": "SZSE:300740",
        "f": [
          "no longer trading"
        ]
      },
      {
        "s": "SZSE:395005",
        "f": [
          "empty symbol"
        ]
      }
    ]
  }