{
    "black_list": [
      {
        "s": "QSE:ABCM",
        "f": [
          "empty symbol"
        ],
        "partial_ban": false
      },
      {
        "s": "QSE:ABCR",
        "f": [
          "empty symbol"
        ],
        "partial_ban": false
      },
      {
        "s": "QSE:QABC",
        "f": [
          "empty symbol"
        ],
        "partial_ban": false
      },
      {
        "s": "QSE:QCBD",
        "f": [
          "empty symbol"
        ],
        "partial_ban": false
      }
    ]
  }